lavd/__init__.py
lavd/data.py
lavd/file_types.py
lavd/fs.py
lavd/log.py
lavd/noop.py
lavd/server.py
lavd/version.py
lavd/static/index.html
lavd/static/assets/index.aebe0b73.css
lavd/static/assets/index.c1c0e49e.js
lavd/static/assets/index.c1c0e49e.js.map
lavd/static/assets/vendor.ac84dfc1.js
lavd/static/assets/vendor.ac84dfc1.js.map
lavd-0.2.7.dist-info/LICENSE.md
lavd-0.2.7.dist-info/METADATA
lavd-0.2.7.dist-info/WHEEL
lavd-0.2.7.dist-info/entry_points.txt
lavd-0.2.7.dist-info/top_level.txt
lavd-0.2.7.dist-info/RECORD
