Metadata-Version: 2.1
Name: lavd
Version: 0.2.7
Summary: Log and Visualise Data
Home-page: https://github.com/jungomi/lavd
Author: Michael Jungo
Author-email: michaeljungo92@gmail.com
License: MIT
Keywords: log,visualise,visualize,data
Classifier: Development Status :: 4 - Beta
Classifier: License :: OSI Approved :: MIT License
Classifier: Programming Language :: Python :: 3.9
Classifier: Programming Language :: Python :: 3.10
Classifier: Programming Language :: Python :: 3.11
Classifier: Operating System :: OS Independent
Classifier: Topic :: System :: Logging
Classifier: Topic :: Scientific/Engineering :: Visualization
Classifier: Typing :: Typed
Requires-Python: >=3.9
License-File: LICENSE.md
Requires-Dist: halo
Requires-Dist: Pillow
Requires-Dist: simplejson
Requires-Dist: tornado
Requires-Dist: tqdm
Requires-Dist: watchdog
